MANIFEST.in
README.rst
development.txt
requirements.txt
setup.cfg
setup.py
docs/Makefile
docs/make.bat
docs/source/api.rst
docs/source/cli.rst
docs/source/conf.py
docs/source/index.rst
privacy/__init__.py
privacy/aes.py
privacy/conf.py
privacy/core.py
privacy/util.py
privacy/version.py
privacy.egg-info/PKG-INFO
privacy.egg-info/SOURCES.txt
privacy.egg-info/dependency_links.txt
privacy.egg-info/entry_points.txt
privacy.egg-info/not-zip-safe
privacy.egg-info/requires.txt
privacy.egg-info/top_level.txt
privacy/console/__init__.py
privacy/console/base.py
privacy/console/crypto.py
privacy/console/keys.py
privacy/console/main.py
privacy/console/operations.py
privacy/console/ui.py
privacy/console/util.py
privacy/console/parsers/__init__.py
privacy/console/parsers/backup.py
privacy/console/parsers/decrypt.py
privacy/console/parsers/delete_key.py
privacy/console/parsers/encrypt.py
privacy/console/parsers/generate_key.py
privacy/console/parsers/import_key.py
privacy/console/parsers/list_keys.py
privacy/console/parsers/quickstart.py
privacy/console/parsers/recover.py
privacy/console/parsers/show.py
privacy/console/parsers/show_passphrase.py
privacy/console/parsers/show_private.py
privacy/console/parsers/show_public.py
privacy/console/parsers/sign.py
privacy/console/parsers/verify.py
privacy/console/parsers/wipe.py