Metadata-Version: 1.0
Name: privacy
Version: 0.0.1
Summary: Create/Manage/List GPG Keys and Encrypt/Decrypt things with them
Home-page: https://github.com/gabrielfalcao/privacy
Author: Gabriel Falcao
Author-email: gabriel@nacaolivre.org
License: UNKNOWN
Platform: UNKNOWN
